Workbook

Sheet README
A1: La Haute Borne wind farm: asset P&L and variance analysis, 2015
A2: Companion to github.com/syulimo/wind-performance-analysis
A4: Purpose | B4: Asset-management view of the same SCADA analysis: budget vs actual, variance bridge by driver, turbine ranking, reforecast.
A5: Operating year | B5: 2015. Budget is set ex ante from 2014 data only, so 2015 is analysed out of sample.
A6: Budget (P50 proxy) | B6: 2014 potential energy, long-term corrected with an ERA5 wind index (1999 to 2013), spread by the long-term monthly profile.
A7: Revenue | B7: Energy x tariff. The tariff on Inputs is an editable assumption; change it to see every euro figure update.
A8: Data sources | B8: outputs/loss_monthly.csv from the pipeline (ENGIE La Haute Borne SCADA via NREL OpenOA); ERA5 100 m wind speed from the same OpenOA dataset.
A9: Not included | B9: O&M, land, insurance and other costs: no public cost data exist for this site, so the P&L stops at revenue and lost revenue.
A10: Colour legend | B10: Blue text = hardcoded input or imported data. Black = formula. Green = direct link to another sheet. Yellow fill = assumption to edit.
A11: How to use | B11: Edit the yellow cells on Inputs (tariff, months of actuals). Everything else recalculates.

Sheet Inputs
A1: Inputs and budget
A2: Edit yellow cells only
A4: Item | B4: Value | C4: Unit | D4: Source / note
A5: Tariff | B5: 82 | C5: €/MWh | D5: Assumption: French onshore wind feed-in tariff base level (arrêté of 17 Nov 2008, 8.2 c€/kWh), before annual indexation. Edit to test other prices or a PPA.
A6: Months of actuals for reforecast | B6: 6 | C6: months | D6: Reforecast sheet uses actuals for months 1 to this number, budget after. Enter 1 to 11.
A8: Budget build (formulas)
A9: 2014 potential energy, fleet | B9: =SUMIFS(Data_Monthly!$E:$E,Data_Monthly!$I:$I,2014) -> 11454.794 | C9: MWh | D9: Expected energy from the reference power curves, 2014 (pipeline output)
A10: Long-term / 2014 wind index ratio | B10: =SUM(Wind_Index!$B$5:$B$16)/SUM(Wind_Index!$C$5:$C$16) -> 1.1642742 | C10: x | D10: ERA5 1999 to 2013 mean over 2014; above 1 means 2014 was a low-wind year
A11: Annual budget, P50 proxy | B11: =B9*B10 -> 13336.522 | C11: MWh | D11: Spread across months by the long-term monthly profile on Wind_Index
A12: Annual budget revenue | B12: =B11*B5 -> 1093594.8 | C12: €

Sheet Wind_Index
A1: ERA5 wind energy index by month
A2: Mean of min(max(ws100 - 3, 0)^3 / 9^3, 1), hourly ERA5 100 m wind speed at the site; computed in src/wpa/build_asset_pnl.py
A4: Month | B4: Long-term 1999-2013 | C4: 2014 | D4: 2015 | E4: Budget share of year | F4: 2015 vs long-term
A5: Jan | B5: 0.216188 | C5: 0.230876 | D5: 0.264539 | E5: =B5/SUM($B$5:$B$16) -> 0.13657631 | F5: =D5/B5-1 -> 0.22365256
A6: Feb | B6: 0.198475 | C6: 0.32558 | D6: 0.174423 | E6: =B6/SUM($B$5:$B$16) -> 0.12538616 | F6: =D6/B6-1 -> -0.12118403
A7: Mar | B7: 0.163287 | C7: 0.074634 | D7: 0.159186 | E7: =B7/SUM($B$5:$B$16) -> 0.10315621 | F7: =D7/B7-1 -> -0.025115288
A8: Apr | B8: 0.108607 | C8: 0.044326 | D8: 0.092369 | E8: =B8/SUM($B$5:$B$16) -> 0.068612239 | F8: =D8/B8-1 -> -0.14951154
A9: May | B9: 0.079852 | C9: 0.114362 | D9: 0.076558 | E9: =B9/SUM($B$5:$B$16) -> 0.05044633 | F9: =D9/B9-1 -> -0.041251315
A10: Jun | B10: 0.055375 | C10: 0.048424 | D10: 0.049769 | E10: =B10/SUM($B$5:$B$16) -> 0.034983038 | F10: =D10/B10-1 -> -0.10123702
A11: Jul | B11: 0.064838 | C11: 0.047633 | D11: 0.079524 | E11: =B11/SUM($B$5:$B$16) -> 0.040961268 | F11: =D11/B11-1 -> 0.22650298
A12: Aug | B12: 0.052459 | C12: 0.046732 | D12: 0.064658 | E12: =B12/SUM($B$5:$B$16) -> 0.033140861 | F12: =D12/B12-1 -> 0.23254351
A13: Sep | B13: 0.077878 | C13: 0.0293 | D13: 0.168152 | E13: =B13/SUM($B$5:$B$16) -> 0.04919926 | F13: =D13/B13-1 -> 1.159172
A14: Oct | B14: 0.146565 | C14: 0.100686 | D14: 0.055879 | E14: =B14/SUM($B$5:$B$16) -> 0.092592125 | F14: =D14/B14-1 -> -0.61874254
A15: Nov | B15: 0.170622 | C15: 0.107405 | D15: 0.234623 | E15: =B15/SUM($B$5:$B$16) -> 0.10779008 | F15: =D15/B15-1 -> 0.37510403
A16: Dec | B16: 0.248764 | C16: 0.18961 | D16: 0.18133 | E16: =B16/SUM($B$5:$B$16) -> 0.15715612 | F16: =D16/B16-1 -> -0.2710762
A17: Year | B17: =SUM(B5:B16) -> 1.58291 | C17: =SUM(C5:C16) -> 1.359568 | D17: =SUM(D5:D16) -> 1.60101 | F17: =D17/B17-1 -> 0.011434636

Sheet Data_Monthly
A1: Monthly energy by turbine (pipeline output)
A2: Source: outputs/loss_monthly.csv, written by src/wpa/pipeline.py from 10-minute SCADA. MWh.
A4: Turbine | B4: Month | C4: Actual MWh | D4: (blank) | E4: Potential MWh | F4: Downtime MWh | G4: Underperf. MWh | H4: Icing MWh | I4: Year | J4: Month no. | K4: Curtailment MWh
A5: R80711 | B5: 41640 | C5: 376.238 | E5: 369.831 | F5: 0.017 | G5: 0.57 | H5: 0.063 | I5: =YEAR(B5) -> 2014 | J5: =MONTH(B5) -> 1 | K5: 0
A6: R80711 | B6: 41671 | C6: 502.542 | E6: 499.006 | F6: 0.263 | G6: 0.653 | H6: 0.031 | I6: =YEAR(B6) -> 2014 | J6: =MONTH(B6) -> 2 | K6: 0
A7: R80711 | B7: 41699 | C7: 230.081 | E7: 230.849 | F7: 0.006 | G7: 1.463 | H7: 0 | I7: =YEAR(B7) -> 2014 | J7: =MONTH(B7) -> 3 | K7: 0
A8: R80711 | B8: 41730 | C8: 183.188 | E8: 188.032 | F8: 0.066 | G8: 1.142 | H8: 0 | I8: =YEAR(B8) -> 2014 | J8: =MONTH(B8) -> 4 | K8: 0
A9: R80711 | B9: 41760 | C9: 324.149 | E9: 332.228 | F9: 0.763 | G9: 2.272 | H9: 0 | I9: =YEAR(B9) -> 2014 | J9: =MONTH(B9) -> 5 | K9: 0.051
A10: R80711 | B10: 41791 | C10: 202.695 | E10: 220.459 | F10: 3.554 | G10: 3.829 | H10: 0 | I10: =YEAR(B10) -> 2014 | J10: =MONTH(B10) -> 6 | K10: 0.272
A11: R80711 | B11: 41821 | C11: 182.274 | E11: 193.604 | F11: 0.099 | G11: 3.938 | H11: 0 | I11: =YEAR(B11) -> 2014 | J11: =MONTH(B11) -> 7 | K11: 0.316
A12: R80711 | B12: 41852 | C12: 195.838 | E12: 204.89 | F12: 0.051 | G12: 2.226 | H12: 0 | I12: =YEAR(B12) -> 2014 | J12: =MONTH(B12) -> 8 | K12: 0
A13: R80711 | B13: 41883 | C13: 143.407 | E13: 153.236 | F13: 0.007 | G13: 3.258 | H13: 0 | I13: =YEAR(B13) -> 2014 | J13: =MONTH(B13) -> 9 | K13: 0
A14: R80711 | B14: 41913 | C14: 209.419 | E14: 210.534 | F14: 3.437 | G14: 0.774 | H14: 0 | I14: =YEAR(B14) -> 2014 | J14: =MONTH(B14) -> 10 | K14: 0.13
A15: R80711 | B15: 41944 | C15: 208.921 | E15: 195.371 | F15: 1.945 | G15: 0.441 | H15: 0.089 | I15: =YEAR(B15) -> 2014 | J15: =MONTH(B15) -> 11 | K15: 0
A16: R80711 | B16: 41974 | C16: 392.503 | E16: 396.6 | F16: 5.036 | G16: 1.263 | H16: 2.497 | I16: =YEAR(B16) -> 2014 | J16: =MONTH(B16) -> 12 | K16: 0
... A100: R80790 | B100: 42339 | C100: 347.505 | E100: 340.837 | F100: 0.033 | G100: 3.116 | H100: 0 | I100: =YEAR(B100) -> 2015 | J100: =MONTH(B100) -> 12 | K100: 0

Sheet Fleet_2015
A1: Fleet budget vs actual by month, 2015
A2: Losses shown negative. Check column must be zero: resource + losses + other = variance to budget.
A4: Month no. | B4: Month | C4: Budget MWh | D4: Potential MWh | E4: Wind resource var. | F4: Downtime | G4: Underperf. | H4: Icing | I4: Curtailment | J4: Actual MWh | K4: Other | L4: Variance to budget | M4: Check | N4: Budget revenue | O4: Actual revenue | P4: Revenue variance
A5: 1 | B5: Jan | C5: =Inputs!$B$11*Wind_Index!E5 -> 1821.4528 | D5: =SUMIFS(Data_Monthly!$E$5:$E$100,Data_Monthly!$I$5:$I$100,2015,Data_Monthly!$J$5:$J$100,$A5) -> 1708.657 | E5: =D5-C5 -> -112.79585 | F5: =-SUMIFS(Data_Monthly!$F$5:$F$100,Data_Monthly!$I$5:$I$100,2015,Data_Monthly!$J$5:$J$100,$A5) -> -12.602 | G5: =-SUMIFS(Data_Monthly!$G$5:$G$100,Data_Monthly!$I$5:$I$100,2015,Data_Monthly!$J$5:$J$100,$A5) -> -7.922 | H5: =-SUMIFS(Data_Monthly!$H$5:$H$100,Data_Monthly!$I$5:$I$100,2015,Data_Monthly!$J$5:$J$100,$A5) -> -2.806 | I5: =-SUMIFS(Data_Monthly!$K$5:$K$100,Data_Monthly!$I$5:$I$100,2015,Data_Monthly!$J$5:$J$100,$A5) -> 0 | J5: =SUMIFS(Data_Monthly!$C$5:$C$100,Data_Monthly!$I$5:$I$100,2015,Data_Monthly!$J$5:$J$100,$A5) -> 1697.069 | K5: =J5-D5-SUM(F5:I5) -> 11.742 | L5: =J5-C5 -> -124.38385 | M5: =ROUND(E5+SUM(F5:I5)+K5-L5,6) -> 0 | N5: =C5*Inputs!$B$5 -> 149359.13 | O5: =J5*Inputs!$B$5 -> 139159.66 | P5: =O5-N5 -> -10199.476
A6: 2 | B6: Feb | C6: =Inputs!$B$11*Wind_Index!E6 -> 1672.2152 | D6: =SUMIFS(Data_Monthly!$E$5:$E$100,Data_Monthly!$I$5:$I$100,2015,Data_Monthly!$J$5:$J$100,$A6) -> 1153.22 | E6: =D6-C6 -> -518.99517 | F6: =-SUMIFS(Data_Monthly!$F$5:$F$100,Data_Monthly!$I$5:$I$100,2015,Data_Monthly!$J$5:$J$100,$A6) -> -35.056 | G6: =-SUMIFS(Data_Monthly!$G$5:$G$100,Data_Monthly!$I$5:$I$100,2015,Data_Monthly!$J$5:$J$100,$A6) -> -5.385 | H6: =-SUMIFS(Data_Monthly!$H$5:$H$100,Data_Monthly!$I$5:$I$100,2015,Data_Monthly!$J$5:$J$100,$A6) -> -0.385 | I6: =-SUMIFS(Data_Monthly!$K$5:$K$100,Data_Monthly!$I$5:$I$100,2015,Data_Monthly!$J$5:$J$100,$A6) -> 0 | J6: =SUMIFS(Data_Monthly!$C$5:$C$100,Data_Monthly!$I$5:$I$100,2015,Data_Monthly!$J$5:$J$100,$A6) -> 1178.683 | K6: =J6-D6-SUM(F6:I6) -> 66.289 | L6: =J6-C6 -> -493.53217 | M6: =ROUND(E6+SUM(F6:I6)+K6-L6,6) -> 0 | N6: =C6*Inputs!$B$5 -> 137121.64 | O6: =J6*Inputs!$B$5 -> 96652.006 | P6: =O6-N6 -> -40469.638
A7: 3 | B7: Mar | C7: =Inputs!$B$11*Wind_Index!E7 -> 1375.7451 | D7: =SUMIFS(Data_Monthly!$E$5:$E$100,Data_Monthly!$I$5:$I$100,2015,Data_Monthly!$J$5:$J$100,$A7) -> 1276.401 | E7: =D7-C7 -> -99.344051 | F7: =-SUMIFS(Data_Monthly!$F$5:$F$100,Data_Monthly!$I$5:$I$100,2015,Data_Monthly!$J$5:$J$100,$A7) -> -0.808 | G7: =-SUMIFS(Data_Monthly!$G$5:$G$100,Data_Monthly!$I$5:$I$100,2015,Data_Monthly!$J$5:$J$100,$A7) -> -5.194 | H7: =-SUMIFS(Data_Monthly!$H$5:$H$100,Data_Monthly!$I$5:$I$100,2015,Data_Monthly!$J$5:$J$100,$A7) -> -0.031 | I7: =-SUMIFS(Data_Monthly!$K$5:$K$100,Data_Monthly!$I$5:$I$100,2015,Data_Monthly!$J$5:$J$100,$A7) -> 0 | J7: =SUMIFS(Data_Monthly!$C$5:$C$100,Data_Monthly!$I$5:$I$100,2015,Data_Monthly!$J$5:$J$100,$A7) -> 1289.368 | K7: =J7-D7-SUM(F7:I7) -> 19 | L7: =J7-C7 -> -86.377051 | M7: =ROUND(E7+SUM(F7:I7)+K7-L7,6) -> 0 | N7: =C7*Inputs!$B$5 -> 112811.09 | O7: =J7*Inputs!$B$5 -> 105728.18 | P7: =O7-N7 -> -7082.9182
A8: 4 | B8: Apr | C8: =Inputs!$B$11*Wind_Index!E8 -> 915.04861 | D8: =SUMIFS(Data_Monthly!$E$5:$E$100,Data_Monthly!$I$5:$I$100,2015,Data_Monthly!$J$5:$J$100,$A8) -> 964.139 | E8: =D8-C8 -> 49.090388 | F8: =-SUMIFS(Data_Monthly!$F$5:$F$100,Data_Monthly!$I$5:$I$100,2015,Data_Monthly!$J$5:$J$100,$A8) -> -20.621 | G8: =-SUMIFS(Data_Monthly!$G$5:$G$100,Data_Monthly!$I$5:$I$100,2015,Data_Monthly!$J$5:$J$100,$A8) -> -7.5 | H8: =-SUMIFS(Data_Monthly!$H$5:$H$100,Data_Monthly!$I$5:$I$100,2015,Data_Monthly!$J$5:$J$100,$A8) -> 0 | I8: =-SUMIFS(Data_Monthly!$K$5:$K$100,Data_Monthly!$I$5:$I$100,2015,Data_Monthly!$J$5:$J$100,$A8) -> 0 | J8: =SUMIFS(Data_Monthly!$C$5:$C$100,Data_Monthly!$I$5:$I$100,2015,Data_Monthly!$J$5:$J$100,$A8) -> 959.749 | K8: =J8-D8-SUM(F8:I8) -> 23.731 | L8: =J8-C8 -> 44.700388 | M8: =ROUND(E8+SUM(F8:I8)+K8-L8,6) -> 0 | N8: =C8*Inputs!$B$5 -> 75033.986 | O8: =J8*Inputs!$B$5 -> 78699.418 | P8: =O8-N8 -> 3665.4318
A9: 5 | B9: May | C9: =Inputs!$B$11*Wind_Index!E9 -> 672.77857 | D9: =SUMIFS(Data_Monthly!$E$5:$E$100,Data_Monthly!$I$5:$I$100,2015,Data_Monthly!$J$5:$J$100,$A9) -> 977.815 | E9: =D9-C9 -> 305.03643 | F9: =-SUMIFS(Data_Monthly!$F$5:$F$100,Data_Monthly!$I$5:$I$100,2015,Data_Monthly!$J$5:$J$100,$A9) -> -27.95 | G9: =-SUMIFS(Data_Monthly!$G$5:$G$100,Data_Monthly!$I$5:$I$100,2015,Data_Monthly!$J$5:$J$100,$A9) -> -7.078 | H9: =-SUMIFS(Data_Monthly!$H$5:$H$100,Data_Monthly!$I$5:$I$100,2015,Data_Monthly!$J$5:$J$100,$A9) -> 0 | I9: =-SUMIFS(Data_Monthly!$K$5:$K$100,Data_Monthly!$I$5:$I$100,2015,Data_Monthly!$J$5:$J$100,$A9) -> 0 | J9: =SUMIFS(Data_Monthly!$C$5:$C$100,Data_Monthly!$I$5:$I$100,2015,Data_Monthly!$J$5:$J$100,$A9) -> 947.7 | K9: =J9-D9-SUM(F9:I9) -> 4.913 | L9: =J9-C9 -> 274.92143 | M9: =ROUND(E9+SUM(F9:I9)+K9-L9,6) -> 0 | N9: =C9*Inputs!$B$5 -> 55167.842 | O9: =J9*Inputs!$B$5 -> 77711.4 | P9: =O9-N9 -> 22543.558
A10: 6 | B10: Jun | C10: =Inputs!$B$11*Wind_Index!E10 -> 466.55204 | D10: =SUMIFS(Data_Monthly!$E$5:$E$100,Data_Monthly!$I$5:$I$100,2015,Data_Monthly!$J$5:$J$100,$A10) -> 749.331 | E10: =D10-C10 -> 282.77896 | F10: =-SUMIFS(Data_Monthly!$F$5:$F$100,Data_Monthly!$I$5:$I$100,2015,Data_Monthly!$J$5:$J$100,$A10) -> -6.471 | G10: =-SUMIFS(Data_Monthly!$G$5:$G$100,Data_Monthly!$I$5:$I$100,2015,Data_Monthly!$J$5:$J$100,$A10) -> -8.645 | H10: =-SUMIFS(Data_Monthly!$H$5:$H$100,Data_Monthly!$I$5:$I$100,2015,Data_Monthly!$J$5:$J$100,$A10) -> 0 | I10: =-SUMIFS(Data_Monthly!$K$5:$K$100,Data_Monthly!$I$5:$I$100,2015,Data_Monthly!$J$5:$J$100,$A10) -> 0 | J10: =SUMIFS(Data_Monthly!$C$5:$C$100,Data_Monthly!$I$5:$I$100,2015,Data_Monthly!$J$5:$J$100,$A10) -> 730.56 | K10: =J10-D10-SUM(F10:I10) -> -3.655 | L10: =J10-C10 -> 264.00796 | M10: =ROUND(E10+SUM(F10:I10)+K10-L10,6) -> 0 | N10: =C10*Inputs!$B$5 -> 38257.267 | O10: =J10*Inputs!$B$5 -> 59905.92 | P10: =O10-N10 -> 21648.653
A11: 7 | B11: Jul | C11: =Inputs!$B$11*Wind_Index!E11 -> 546.28083 | D11: =SUMIFS(Data_Monthly!$E$5:$E$100,Data_Monthly!$I$5:$I$100,2015,Data_Monthly!$J$5:$J$100,$A11) -> 1017.266 | E11: =D11-C11 -> 470.98517 | F11: =-SUMIFS(Data_Monthly!$F$5:$F$100,Data_Monthly!$I$5:$I$100,2015,Data_Monthly!$J$5:$J$100,$A11) -> -43.725 | G11: =-SUMIFS(Data_Monthly!$G$5:$G$100,Data_Monthly!$I$5:$I$100,2015,Data_Monthly!$J$5:$J$100,$A11) -> -19.17 | H11: =-SUMIFS(Data_Monthly!$H$5:$H$100,Data_Monthly!$I$5:$I$100,2015,Data_Monthly!$J$5:$J$100,$A11) -> 0 | I11: =-SUMIFS(Data_Monthly!$K$5:$K$100,Data_Monthly!$I$5:$I$100,2015,Data_Monthly!$J$5:$J$100,$A11) -> -0.875 | J11: =SUMIFS(Data_Monthly!$C$5:$C$100,Data_Monthly!$I$5:$I$100,2015,Data_Monthly!$J$5:$J$100,$A11) -> 914.547 | K11: =J11-D11-SUM(F11:I11) -> -38.949 | L11: =J11-C11 -> 368.26617 | M11: =ROUND(E11+SUM(F11:I11)+K11-L11,6) -> 0 | N11: =C11*Inputs!$B$5 -> 44795.028 | O11: =J11*Inputs!$B$5 -> 74992.854 | P11: =O11-N11 -> 30197.826
A12: 8 | B12: Aug | C12: =Inputs!$B$11*Wind_Index!E12 -> 441.98381 | D12: =SUMIFS(Data_Monthly!$E$5:$E$100,Data_Monthly!$I$5:$I$100,2015,Data_Monthly!$J$5:$J$100,$A12) -> 760.002 | E12: =D12-C12 -> 318.01819 | F12: =-SUMIFS(Data_Monthly!$F$5:$F$100,Data_Monthly!$I$5:$I$100,2015,Data_Monthly!$J$5:$J$100,$A12) -> -8.313 | G12: =-SUMIFS(Data_Monthly!$G$5:$G$100,Data_Monthly!$I$5:$I$100,2015,Data_Monthly!$J$5:$J$100,$A12) -> -11.908 | H12: =-SUMIFS(Data_Monthly!$H$5:$H$100,Data_Monthly!$I$5:$I$100,2015,Data_Monthly!$J$5:$J$100,$A12) -> 0 | I12: =-SUMIFS(Data_Monthly!$K$5:$K$100,Data_Monthly!$I$5:$I$100,2015,Data_Monthly!$J$5:$J$100,$A12) -> 0 | J12: =SUMIFS(Data_Monthly!$C$5:$C$100,Data_Monthly!$I$5:$I$100,2015,Data_Monthly!$J$5:$J$100,$A12) -> 719.857 | K12: =J12-D12-SUM(F12:I12) -> -19.924 | L12: =J12-C12 -> 277.87319 | M12: =ROUND(E12+SUM(F12:I12)+K12-L12,6) -> 0 | N12: =C12*Inputs!$B$5 -> 36242.672 | O12: =J12*Inputs!$B$5 -> 59028.274 | P12: =O12-N12 -> 22785.602
A13: 9 | B13: Sep | C13: =Inputs!$B$11*Wind_Index!E13 -> 656.14699 | D13: =SUMIFS(Data_Monthly!$E$5:$E$100,Data_Monthly!$I$5:$I$100,2015,Data_Monthly!$J$5:$J$100,$A13) -> 1326.324 | E13: =D13-C13 -> 670.17701 | F13: =-SUMIFS(Data_Monthly!$F$5:$F$100,Data_Monthly!$I$5:$I$100,2015,Data_Monthly!$J$5:$J$100,$A13) -> -4.259 | G13: =-SUMIFS(Data_Monthly!$G$5:$G$100,Data_Monthly!$I$5:$I$100,2015,Data_Monthly!$J$5:$J$100,$A13) -> -6.589 | H13: =-SUMIFS(Data_Monthly!$H$5:$H$100,Data_Monthly!$I$5:$I$100,2015,Data_Monthly!$J$5:$J$100,$A13) -> 0 | I13: =-SUMIFS(Data_Monthly!$K$5:$K$100,Data_Monthly!$I$5:$I$100,2015,Data_Monthly!$J$5:$J$100,$A13) -> -0.838 | J13: =SUMIFS(Data_Monthly!$C$5:$C$100,Data_Monthly!$I$5:$I$100,2015,Data_Monthly!$J$5:$J$100,$A13) -> 1341.162 | K13: =J13-D13-SUM(F13:I13) -> 26.524 | L13: =J13-C13 -> 685.01501 | M13: =ROUND(E13+SUM(F13:I13)+K13-L13,6) -> 0 | N13: =C13*Inputs!$B$5 -> 53804.053 | O13: =J13*Inputs!$B$5 -> 109975.28 | P13: =O13-N13 -> 56171.231
A14: 10 | B14: Oct | C14: =Inputs!$B$11*Wind_Index!E14 -> 1234.8569 | D14: =SUMIFS(Data_Monthly!$E$5:$E$100,Data_Monthly!$I$5:$I$100,2015,Data_Monthly!$J$5:$J$100,$A14) -> 575.6 | E14: =D14-C14 -> -659.25687 | F14: =-SUMIFS(Data_Monthly!$F$5:$F$100,Data_Monthly!$I$5:$I$100,2015,Data_Monthly!$J$5:$J$100,$A14) -> -0.487 | G14: =-SUMIFS(Data_Monthly!$G$5:$G$100,Data_Monthly!$I$5:$I$100,2015,Data_Monthly!$J$5:$J$100,$A14) -> -5.464 | H14: =-SUMIFS(Data_Monthly!$H$5:$H$100,Data_Monthly!$I$5:$I$100,2015,Data_Monthly!$J$5:$J$100,$A14) -> 0 | I14: =-SUMIFS(Data_Monthly!$K$5:$K$100,Data_Monthly!$I$5:$I$100,2015,Data_Monthly!$J$5:$J$100,$A14) -> 0 | J14: =SUMIFS(Data_Monthly!$C$5:$C$100,Data_Monthly!$I$5:$I$100,2015,Data_Monthly!$J$5:$J$100,$A14) -> 590.739 | K14: =J14-D14-SUM(F14:I14) -> 21.09 | L14: =J14-C14 -> -644.11787 | M14: =ROUND(E14+SUM(F14:I14)+K14-L14,6) -> 0 | N14: =C14*Inputs!$B$5 -> 101258.26 | O14: =J14*Inputs!$B$5 -> 48440.598 | P14: =O14-N14 -> -52817.665
A15: 11 | B15: Nov | C15: =Inputs!$B$11*Wind_Index!E15 -> 1437.5448 | D15: =SUMIFS(Data_Monthly!$E$5:$E$100,Data_Monthly!$I$5:$I$100,2015,Data_Monthly!$J$5:$J$100,$A15) -> 1667.979 | E15: =D15-C15 -> 230.43423 | F15: =-SUMIFS(Data_Monthly!$F$5:$F$100,Data_Monthly!$I$5:$I$100,2015,Data_Monthly!$J$5:$J$100,$A15) -> -10.33 | G15: =-SUMIFS(Data_Monthly!$G$5:$G$100,Data_Monthly!$I$5:$I$100,2015,Data_Monthly!$J$5:$J$100,$A15) -> -5.951 | H15: =-SUMIFS(Data_Monthly!$H$5:$H$100,Data_Monthly!$I$5:$I$100,2015,Data_Monthly!$J$5:$J$100,$A15) -> -0.075 | I15: =-SUMIFS(Data_Monthly!$K$5:$K$100,Data_Monthly!$I$5:$I$100,2015,Data_Monthly!$J$5:$J$100,$A15) -> -0.144 | J15: =SUMIFS(Data_Monthly!$C$5:$C$100,Data_Monthly!$I$5:$I$100,2015,Data_Monthly!$J$5:$J$100,$A15) -> 1665.998 | K15: =J15-D15-SUM(F15:I15) -> 14.519 | L15: =J15-C15 -> 228.45323 | M15: =ROUND(E15+SUM(F15:I15)+K15-L15,6) -> 0 | N15: =C15*Inputs!$B$5 -> 117878.67 | O15: =J15*Inputs!$B$5 -> 136611.84 | P15: =O15-N15 -> 18733.165
A16: 12 | B16: Dec | C16: =Inputs!$B$11*Wind_Index!E16 -> 2095.916 | D16: =SUMIFS(Data_Monthly!$E$5:$E$100,Data_Monthly!$I$5:$I$100,2015,Data_Monthly!$J$5:$J$100,$A16) -> 1302.685 | E16: =D16-C16 -> -793.23104 | F16: =-SUMIFS(Data_Monthly!$F$5:$F$100,Data_Monthly!$I$5:$I$100,2015,Data_Monthly!$J$5:$J$100,$A16) -> -0.489 | G16: =-SUMIFS(Data_Monthly!$G$5:$G$100,Data_Monthly!$I$5:$I$100,2015,Data_Monthly!$J$5:$J$100,$A16) -> -5.889 | H16: =-SUMIFS(Data_Monthly!$H$5:$H$100,Data_Monthly!$I$5:$I$100,2015,Data_Monthly!$J$5:$J$100,$A16) -> 0 | I16: =-SUMIFS(Data_Monthly!$K$5:$K$100,Data_Monthly!$I$5:$I$100,2015,Data_Monthly!$J$5:$J$100,$A16) -> 0 | J16: =SUMIFS(Data_Monthly!$C$5:$C$100,Data_Monthly!$I$5:$I$100,2015,Data_Monthly!$J$5:$J$100,$A16) -> 1363.66 | K16: =J16-D16-SUM(F16:I16) -> 67.353 | L16: =J16-C16 -> -732.25604 | M16: =ROUND(E16+SUM(F16:I16)+K16-L16,6) -> 0 | N16: =C16*Inputs!$B$5 -> 171865.12 | O16: =J16*Inputs!$B$5 -> 111820.12 | P16: =O16-N16 -> -60044.995
B17: 2015 | C17: =SUM(C5:C16) -> 13336.522 | D17: =SUM(D5:D16) -> 13479.419 | E17: =SUM(E5:E16) -> 142.89742 | F17: =SUM(F5:F16) -> -171.111 | G17: =SUM(G5:G16) -> -96.695 | H17: =SUM(H5:H16) -> -3.297 | I17: =SUM(I5:I16) -> -1.857 | J17: =SUM(J5:J16) -> 13399.092 | ... P17: =SUM(P5:P16) -> 5130.7745
A19: Variance to budget, % | C19: =IFERROR(L17/C17,0) -> 0.0046916597
A20: Reading: the wind resource column is what the weather did; downtime to curtailment are what operations lost; other is curve scatter and records excluded by data quality.

Sheet Bridge
A1: 2015 revenue bridge: budget to actual
A2: Each step links to Fleet_2015 totals; euros = MWh x tariff
A4: Step | B4: MWh | C4: € | D4: Share of budget
A5: Budget | B5: =Fleet_2015!C17 -> 13336.522 | C5: =B5*Inputs!$B$5 -> 1093594.8 | D5: =IFERROR(B5/$B$5,0) -> 1
A6: Wind resource | B6: =Fleet_2015!E17 -> 142.89742 | C6: =B6*Inputs!$B$5 -> 11717.588 | D6: =IFERROR(B6/$B$5,0) -> 0.010714744
A7: Downtime | B7: =Fleet_2015!F17 -> -171.111 | C7: =B7*Inputs!$B$5 -> -14031.102 | D7: =IFERROR(B7/$B$5,0) -> -0.012830257
A8: Underperformance | B8: =Fleet_2015!G17 -> -96.695 | C8: =B8*Inputs!$B$5 -> -7928.99 | D8: =IFERROR(B8/$B$5,0) -> -0.0072503913
A9: Icing | B9: =Fleet_2015!H17 -> -3.297 | C9: =B9*Inputs!$B$5 -> -270.354 | D9: =IFERROR(B9/$B$5,0) -> -0.00024721589
A10: Curtailment | B10: =Fleet_2015!I17 -> -1.857 | C10: =B10*Inputs!$B$5 -> -152.274 | D10: =IFERROR(B10/$B$5,0) -> -0.0001392417
A11: Other | B11: =Fleet_2015!K17 -> 192.633 | C11: =B11*Inputs!$B$5 -> 15795.906 | D11: =IFERROR(B11/$B$5,0) -> 0.014444021
A12: Actual | B12: =Fleet_2015!J17 -> 13399.092 | C12: =B12*Inputs!$B$5 -> 1098725.5 | D12: =IFERROR(B12/$B$5,0) -> 1.0046917
A14: Check: budget + steps - actual | B14: =ROUND(B5+SUM(B6:B11)-B12,6) -> 0
A15: Operational losses, € (downtime to curtailment) | C15: =SUM(C7:C10) -> -22382.72
A16: Largest operational driver | C16: =INDEX(A7:A10,MATCH(MIN(C7:C10),C7:C10,0)) -> Downtime

Sheet Turbine_2015
A1: Turbine ranking by lost energy and lost revenue, 2015
A2: Rank 1 = most lost energy; act on it first
A4: Turbine | B4: Actual MWh | C4: Potential MWh | D4: Downtime | E4: Underperf. | F4: Icing | G4: Curtailment | H4: Total lost MWh | I4: Lost revenue | J4: Share of fleet loss | K4: Rank | L4: Underperf. 2014 | M4: Underperf. change
A5: R80711 | B5: =SUMIFS(Data_Monthly!$C$5:$C$100,Data_Monthly!$I$5:$I$100,2015,Data_Monthly!$A$5:$A$100,$A5) -> 3801.926 | C5: =SUMIFS(Data_Monthly!$E$5:$E$100,Data_Monthly!$I$5:$I$100,2015,Data_Monthly!$A$5:$A$100,$A5) -> 3771.809 | D5: =SUMIFS(Data_Monthly!$F$5:$F$100,Data_Monthly!$I$5:$I$100,2015,Data_Monthly!$A$5:$A$100,$A5) -> 57.806 | E5: =SUMIFS(Data_Monthly!$G$5:$G$100,Data_Monthly!$I$5:$I$100,2015,Data_Monthly!$A$5:$A$100,$A5) -> 20.82 | F5: =SUMIFS(Data_Monthly!$H$5:$H$100,Data_Monthly!$I$5:$I$100,2015,Data_Monthly!$A$5:$A$100,$A5) -> 1.197 | G5: =SUMIFS(Data_Monthly!$K$5:$K$100,Data_Monthly!$I$5:$I$100,2015,Data_Monthly!$A$5:$A$100,$A5) -> 0.54 | H5: =SUM(D5:G5) -> 80.363 | I5: =H5*Inputs!$B$5 -> 6589.766 | J5: =IFERROR(H5/SUM($H$5:$H$8),0) -> 0.2944131 | K5: =RANK(H5,$H$5:$H$8,0) -> 2 | L5: =SUMIFS(Data_Monthly!$G$5:$G$100,Data_Monthly!$I$5:$I$100,2014,Data_Monthly!$A$5:$A$100,$A5) -> 21.829 | M5: =E5-L5 -> -1.009
A6: R80721 | B6: =SUMIFS(Data_Monthly!$C$5:$C$100,Data_Monthly!$I$5:$I$100,2015,Data_Monthly!$A$5:$A$100,$A6) -> 2951 | C6: =SUMIFS(Data_Monthly!$E$5:$E$100,Data_Monthly!$I$5:$I$100,2015,Data_Monthly!$A$5:$A$100,$A6) -> 2955.68 | D6: =SUMIFS(Data_Monthly!$F$5:$F$100,Data_Monthly!$I$5:$I$100,2015,Data_Monthly!$A$5:$A$100,$A6) -> 19.274 | E6: =SUMIFS(Data_Monthly!$G$5:$G$100,Data_Monthly!$I$5:$I$100,2015,Data_Monthly!$A$5:$A$100,$A6) -> 19.874 | F6: =SUMIFS(Data_Monthly!$H$5:$H$100,Data_Monthly!$I$5:$I$100,2015,Data_Monthly!$A$5:$A$100,$A6) -> 0.78 | G6: =SUMIFS(Data_Monthly!$K$5:$K$100,Data_Monthly!$I$5:$I$100,2015,Data_Monthly!$A$5:$A$100,$A6) -> 0.39 | H6: =SUM(D6:G6) -> 40.318 | I6: =H6*Inputs!$B$5 -> 3306.076 | J6: =IFERROR(H6/SUM($H$5:$H$8),0) -> 0.14770662 | K6: =RANK(H6,$H$5:$H$8,0) -> 4 | L6: =SUMIFS(Data_Monthly!$G$5:$G$100,Data_Monthly!$I$5:$I$100,2014,Data_Monthly!$A$5:$A$100,$A6) -> 14.342 | M6: =E6-L6 -> 5.532
A7: R80736 | B7: =SUMIFS(Data_Monthly!$C$5:$C$100,Data_Monthly!$I$5:$I$100,2015,Data_Monthly!$A$5:$A$100,$A7) -> 3207.897 | C7: =SUMIFS(Data_Monthly!$E$5:$E$100,Data_Monthly!$I$5:$I$100,2015,Data_Monthly!$A$5:$A$100,$A7) -> 3230.096 | D7: =SUMIFS(Data_Monthly!$F$5:$F$100,Data_Monthly!$I$5:$I$100,2015,Data_Monthly!$A$5:$A$100,$A7) -> 32.387 | E7: =SUMIFS(Data_Monthly!$G$5:$G$100,Data_Monthly!$I$5:$I$100,2015,Data_Monthly!$A$5:$A$100,$A7) -> 16.871 | F7: =SUMIFS(Data_Monthly!$H$5:$H$100,Data_Monthly!$I$5:$I$100,2015,Data_Monthly!$A$5:$A$100,$A7) -> 0.458 | G7: =SUMIFS(Data_Monthly!$K$5:$K$100,Data_Monthly!$I$5:$I$100,2015,Data_Monthly!$A$5:$A$100,$A7) -> 0.429 | H7: =SUM(D7:G7) -> 50.145 | I7: =H7*Inputs!$B$5 -> 4111.89 | J7: =IFERROR(H7/SUM($H$5:$H$8),0) -> 0.18370824 | K7: =RANK(H7,$H$5:$H$8,0) -> 3 | L7: =SUMIFS(Data_Monthly!$G$5:$G$100,Data_Monthly!$I$5:$I$100,2014,Data_Monthly!$A$5:$A$100,$A7) -> 14.781 | M7: =E7-L7 -> 2.09
A8: R80790 | B8: =SUMIFS(Data_Monthly!$C$5:$C$100,Data_Monthly!$I$5:$I$100,2015,Data_Monthly!$A$5:$A$100,$A8) -> 3438.269 | C8: =SUMIFS(Data_Monthly!$E$5:$E$100,Data_Monthly!$I$5:$I$100,2015,Data_Monthly!$A$5:$A$100,$A8) -> 3521.834 | D8: =SUMIFS(Data_Monthly!$F$5:$F$100,Data_Monthly!$I$5:$I$100,2015,Data_Monthly!$A$5:$A$100,$A8) -> 61.644 | E8: =SUMIFS(Data_Monthly!$G$5:$G$100,Data_Monthly!$I$5:$I$100,2015,Data_Monthly!$A$5:$A$100,$A8) -> 39.13 | F8: =SUMIFS(Data_Monthly!$H$5:$H$100,Data_Monthly!$I$5:$I$100,2015,Data_Monthly!$A$5:$A$100,$A8) -> 0.862 | G8: =SUMIFS(Data_Monthly!$K$5:$K$100,Data_Monthly!$I$5:$I$100,2015,Data_Monthly!$A$5:$A$100,$A8) -> 0.498 | H8: =SUM(D8:G8) -> 102.134 | I8: =H8*Inputs!$B$5 -> 8374.988 | J8: =IFERROR(H8/SUM($H$5:$H$8),0) -> 0.37417204 | K8: =RANK(H8,$H$5:$H$8,0) -> 1 | L8: =SUMIFS(Data_Monthly!$G$5:$G$100,Data_Monthly!$I$5:$I$100,2014,Data_Monthly!$A$5:$A$100,$A8) -> 20.371 | M8: =E8-L8 -> 18.759
A9: Fleet | B9: =SUM(B5:B8) -> 13399.092 | C9: =SUM(C5:C8) -> 13479.419 | D9: =SUM(D5:D8) -> 171.111 | E9: =SUM(E5:E8) -> 96.695 | F9: =SUM(F5:F8) -> 3.297 | G9: =SUM(G5:G8) -> 1.857 | H9: =SUM(H5:H8) -> 272.96 | I9: =SUM(I5:I8) -> 22382.72 | L9: =SUM(L5:L8) -> 71.323 | M9: =SUM(M5:M8) -> 25.372

Sheet Reforecast
A1: Full-year 2015 reforecast
A2: Actuals through the month set on Inputs!B6, budget for the rest of the year
A4: Line | B4: MWh | C4: € | D4: Note
A5: Months of actuals | B5: =Inputs!B6 -> 6 | D5: Set on Inputs
A6: YTD budget | B6: =SUMIFS(Fleet_2015!C5:C16,Fleet_2015!A5:A16,"<="&B5) -> 6923.7923 | C6: =B6*Inputs!$B$5 -> 567750.97
A7: YTD actual | B7: =SUMIFS(Fleet_2015!J5:J16,Fleet_2015!A5:A16,"<="&B5) -> 6803.129 | C7: =B7*Inputs!$B$5 -> 557856.58
A8: YTD potential | B8: =SUMIFS(Fleet_2015!D5:D16,Fleet_2015!A5:A16,"<="&B5) -> 6829.563 | C8: =B8*Inputs!$B$5 -> 560024.17 | D8: Energy the turbines could have made in the actual wind
A9: YTD operating ratio | B9: =IFERROR(B7/B8,0) -> 0.99612947 | D9: Actual / potential: share of available wind energy converted
A10: Rest-of-year budget | B10: =SUMIFS(Fleet_2015!C5:C16,Fleet_2015!A5:A16,">"&B5) -> 6412.7293 | C10: =B10*Inputs!$B$5 -> 525843.8
A11: Reforecast A: YTD actual + budget | B11: =B7+B10 -> 13215.858 | C11: =B11*Inputs!$B$5 -> 1083700.4 | D11: Assumes rest of year at budget
A12: Reforecast B: YTD actual + budget x operating ratio | B12: =B7+B10*B9 -> 13191.038 | C12: =B12*Inputs!$B$5 -> 1081665.1 | D12: Carries YTD operational losses forward; normal wind assumed
A13: Full-year budget | B13: =Fleet_2015!C17 -> 13336.522 | C13: =B13*Inputs!$B$5 -> 1093594.8
A14: Full-year actual (for back-test) | B14: =Fleet_2015!J17 -> 13399.092 | C14: =B14*Inputs!$B$5 -> 1098725.5 | D14: Known here because 2015 is historical
A15: Error, reforecast A vs actual | B15: =B11-B14 -> -183.23371 | C15: =B15*Inputs!$B$5 -> -15025.164
A16: Error, reforecast B vs actual | B16: =B12-B14 -> -208.05434 | C16: =B16*Inputs!$B$5 -> -17060.456
